dm_api/__init__.py
dm_api/dm_api.py
im_data_manager_api-3.0.0.dist-info/LICENSE
im_data_manager_api-3.0.0.dist-info/METADATA
im_data_manager_api-3.0.0.dist-info/WHEEL
im_data_manager_api-3.0.0.dist-info/top_level.txt
im_data_manager_api-3.0.0.dist-info/RECORD
