Metadata-Version: 2.1
Name: im-data-manager-api
Version: 3.0.0
Summary: Data Manager API Client
Home-page: https://github.com/informaticsmatters/data-manager-api
Author: Alan Christie
Author-email: achristie@informaticsmatters.com
License: MIT
Keywords: api
Platform: any
Classifier: Development Status :: 5 - Production/Stable
Classifier: Environment :: Other Environment
Classifier: Intended Audience :: Developers
Classifier: License :: OSI Approved :: MIT License
Classifier: Programming Language :: Python :: 3.9
Classifier: Programming Language :: Python :: 3.10
Classifier: Topic :: Software Development :: Libraries :: Python Modules
Classifier: Operating System :: POSIX :: Linux
Requires-Python: >=3
License-File: LICENSE
Requires-Dist: authlib (==1.0.1)
Requires-Dist: requests (==2.28.0)
Requires-Dist: wrapt (==1.14.1)
